laonlp/__init__.py
laonlp/corpus/LICENSE-lao-eng-dictionary
laonlp/corpus/Lao-Dictionary.txt
laonlp/corpus/__init__.py
laonlp/corpus/core.py
laonlp/corpus/lao-eng-dictionary.csv
laonlp/corpus/lao-wannaphong.txt
laonlp/corpus/lao_words.py
laonlp/corpus/lo_spellcheck_dict.txt
laonlp/corpus/mopt_dict.py
laonlp/corpus/ptagger_SeqLabeling_corpus.json
laonlp/corpus/ptagger_Yunshan-Cup_corpus.json
laonlp/corpus/stopwords_lao.txt
laonlp/corpus/wiktionary-20210720.txt
laonlp/tag/__init__.py
laonlp/tag/pos_tag.py
laonlp/tokenize/__init__.py
laonlp/tokenize/core.py
laonlp/tokenize/multi_cut.py
laonlp/tokenize/syllable.py
laonlp/translate/__init__.py
laonlp/translate/core.py
laonlp/translate/mopt_dict.py
laonlp/transliterate/__init__.py
laonlp/transliterate/core.py
laonlp/util/__init__.py
laonlp/util/digitconv.py
laonlp/util/lao.py
laonlp/word_vector/__init__.py
laonlp/word_vector/word2vec.py
laonlp-1.3.0.dist-info/licenses/LICENSE
laonlp-1.3.0.dist-info/METADATA
laonlp-1.3.0.dist-info/WHEEL
laonlp-1.3.0.dist-info/top_level.txt
laonlp-1.3.0.dist-info/RECORD
