Metadata-Version: 2.4
Name: LaoNLP
Version: 1.3.0
Summary: Lao Natural Language Processing library
Home-page: https://github.com/wannaphong/laonlp
Author: Wannaphong
Author-email: wannaphong@yahoo.com
License: Apache Software License 2.0
Project-URL: Documentation, https://github.com/wannaphong/LaoNLP/wiki
Project-URL: Source, https://github.com/wannaphong/LaoNLP
Project-URL: Bug Reports, https://github.com/wannaphong/LaoNLP/issues
Keywords: lao,NLP,natural language processing,text analytics,text processing,localization,computational linguistics,Lao language
Classifier: Development Status :: 5 - Production/Stable
Classifier: Programming Language :: Python :: 3
Classifier: Intended Audience :: Developers
Classifier: License :: OSI Approved :: Apache Software License
Classifier: Topic :: Scientific/Engineering :: Artificial Intelligence
Classifier: Topic :: Text Processing
Classifier: Topic :: Text Processing :: General
Classifier: Topic :: Text Processing :: Linguistic
Requires-Python: >=3.6
License-File: LICENSE
Requires-Dist: pythainlp>=3.0.0
Provides-Extra: word-vector
Requires-Dist: scipy<1.11.0; extra == "word-vector"
Requires-Dist: gensim; extra == "word-vector"
Requires-Dist: huggingface-hub; extra == "word-vector"
Provides-Extra: full
Requires-Dist: scipy<1.11.0; extra == "full"
Requires-Dist: gensim; extra == "full"
Requires-Dist: huggingface-hub; extra == "full"
Dynamic: author
Dynamic: author-email
Dynamic: classifier
Dynamic: description
Dynamic: description-content-type
Dynamic: home-page
Dynamic: keywords
Dynamic: license
Dynamic: license-file
Dynamic: project-url
Dynamic: provides-extra
Dynamic: requires-dist
Dynamic: requires-python
Dynamic: summary
